pypale/__init__.py
pypale/pypale.py
pypale-0.1.5.dist-info/LICENSE
pypale-0.1.5.dist-info/WHEEL
pypale-0.1.5.dist-info/METADATA
pypale-0.1.5.dist-info/RECORD
